[{"occurrences":2,"phrase":["remaining battery"],"sentiments":[0.26,0.35,0.5,0.65,0.74]},{"occurrences":2,"phrase":["system running time"],"sentiments":[0.26,0.35,0.5,0.65,0.74]},{"occurrences":2,"phrase":["playing games"],"sentiments":[0.06,0.15,0.3,0.45,0.54]},{"occurrences":2,"phrase":["fast charging"],"sentiments":[0.0016666667,0.0791666667,0.2083333333,0.3375,0.415]},{"occurrences":2,"phrase":["full day"],"sentiments":[0.1816666667,0.2166666667,0.275,0.3333333333,0.3683333333]},{"occurrences":2,"phrase":["eis feature"],"sentiments":[0.04,0.1,0.2,0.3,0.36]},{"occurrences":3,"phrase":["treble support"],"sentiments":[0.04,0.1,0.2,0.275,0.32]}]