[{"occurrences":7,"phrase":["battery life"],"sentiments":[-0.1392857143,-0.0458333333,0.1,0.3625,0.76]},{"occurrences":2,"phrase":["portrait mode"],"sentiments":[0.0778571429,0.1732142857,0.3321428571,0.4910714286,0.5864285714]},{"occurrences":2,"phrase":["was using"],"sentiments":[0.065,0.1625,0.325,0.4875,0.585]},{"occurrences":4,"phrase":["lot"],"sentiments":[0.0,0.0,0.1160714286,0.2991071429,0.4196428571]},{"occurrences":5,"phrase":["camera port"],"sentiments":[-0.02,0.0,0.0444444444,0.16875,0.3675]},{"occurrences":3,"phrase":["wifi"],"sentiments":[0.0,0.0,0.0,0.175,0.28]},{"occurrences":2,"phrase":["standby drain"],"sentiments":[0.0232142857,0.0580357143,0.1160714286,0.1741071429,0.2089285714]},{"occurrences":2,"phrase":["day"],"sentiments":[0.0066666667,0.0166666667,0.0333333333,0.05,0.06]},{"occurrences":2,"phrase":["case"],"sentiments":[-0.14,-0.1166666667,-0.0777777778,-0.0388888889,-0.0155555556]},{"occurrences":3,"phrase":["auto brightness"],"sentiments":[-0.25,-0.15625,0.0,0.0,0.0]}]