[{"occurrences":6,"phrase":["Good luck","good luck"],"sentiments":[0.6714285714,0.7,0.7,0.7,0.7]},{"occurrences":2,"phrase":["developing markets"],"sentiments":[0.43,0.475,0.55,0.625,0.67]},{"occurrences":32,"phrase":["card","card being","external card","internal card","new card"],"sentiments":[-0.0710714286,0.0,0.0,0.0852272727,0.5]},{"occurrences":3,"phrase":["many people"],"sentiments":[0.3,0.375,0.5,0.5,0.5]},{"occurrences":6,"phrase":["safe mode"],"sentiments":[0.5,0.5,0.5,0.5,0.5]},{"occurrences":4,"phrase":["computer"],"sentiments":[0.0,0.0,0.25,0.5,0.5]},{"occurrences":15,"phrase":["battery","battery life","good battery life","great battery life","new battery"],"sentiments":[0.0,0.0994318182,0.25,0.4381944444,0.5]},{"occurrences":5,"phrase":["case"],"sentiments":[0.0,0.0,0.0,0.475,0.49]},{"occurrences":13,"phrase":["Many apps","apps","system apps"],"sentiments":[-0.16,0.0,0.0,0.35,0.47]},{"occurrences":2,"phrase":["text messages"],"sentiments":[0.405,0.4125,0.425,0.4375,0.445]}]