[{"occurrences":2,"phrase":["4000 mAh battery"],"sentiments":[0.5032142857,0.5776785714,0.7017857143,0.8258928571,0.9003571429]},{"occurrences":2,"phrase":["4000mAh battery"],"sentiments":[0.525,0.5625,0.625,0.6875,0.725]},{"occurrences":2,"phrase":["price range"],"sentiments":[0.4075,0.45625,0.5375,0.61875,0.6675]},{"occurrences":3,"phrase":["PRO settings"],"sentiments":[0.2383333333,0.2708333333,0.325,0.5,0.605]},{"occurrences":10,"phrase":["heating issue","heating issues"],"sentiments":[-0.0954166667,0.0,0.0,0.1125,0.54]},{"occurrences":2,"phrase":["security patches"],"sentiments":[0.26375,0.303125,0.36875,0.434375,0.47375]},{"occurrences":2,"phrase":["buy"],"sentiments":[0.05,0.125,0.25,0.375,0.45]},{"occurrences":8,"phrase":["battery","battery problem","battery setting"],"sentiments":[-0.1916666667,-0.1166666667,0.0,0.09375,0.4425]},{"occurrences":3,"phrase":["16:9 ratio"],"sentiments":[0.0424242424,0.1060606061,0.2121212121,0.3328463203,0.4052813853]},{"occurrences":3,"phrase":["play store"],"sentiments":[0.0,0.0,0.0,0.25,0.4]}]