[{"occurrences":2,"phrase":["power button"],"sentiments":[-0.91,-0.775,-0.55,-0.325,-0.19]},{"occurrences":4,"phrase":["crap"],"sentiments":[-0.8,-0.8,-0.5375,-0.275,-0.275]},{"occurrences":4,"phrase":["fm radio"],"sentiments":[-0.7,-0.25,0.0,0.125,0.35]},{"occurrences":8,"phrase":["others"],"sentiments":[-0.65,-0.125,0.05,0.2541666667,0.2991666667]},{"occurrences":3,"phrase":["geniune review"],"sentiments":[-0.64,-0.4,0.0,0.0,0.0]},{"occurrences":3,"phrase":["first impression"],"sentiments":[-0.64,-0.4,0.0,0.0,0.0]},{"occurrences":2,"phrase":["poor display"],"sentiments":[-0.615,-0.4875,-0.275,-0.0625,0.065]},{"occurrences":14,"phrase":["customer care","customer service","customer support","sales service"],"sentiments":[-0.54625,-0.10375,0.0,0.2140625,0.4466666667]},{"occurrences":3,"phrase":["apple store"],"sentiments":[-0.4766666667,-0.3666666667,-0.1833333333,0.0144047619,0.133047619]},{"occurrences":2,"phrase":["common sense"],"sentiments":[-0.45171875,-0.359765625,-0.2065104167,-0.0532552083,0.0386979167]}]