{"count":{"alcatel Flash":65,"OnePlus One":62,"Motorola Moto X Play":35,"Motorola Moto X Style":20,"OnePlus 3":19,"Xiaomi Redmi Note 4":17,"Motorola Moto X":17,"LG Nexus 5X":16,"Apple iPhone 5s":13,"Motorola Nexus 6":12,"Xiaomi Redmi Note 5":12,"Apple iPhone 6":10,"OnePlus X":8,"Asus Zenfone 3 Laser ZC551KL":7,"Oppo A53":6,"Oppo A57":6,"Motorola Moto G":5,"Google Pixel":4,"Lenovo Vibe P1 Turbo":4,"Xiaomi Mi 5":4,"Apple iPhone 6 Plus":4,"Xiaomi Mi Note 3":4,"Apple iPhone 6s":4,"BLU Advance 4.0 L3":3,"Motorola Moto G4 Plus":3,"verykool s4009 Crystal":3,"Meizu MX5":3,"YU Yutopia":2,"Samsung Galaxy J5":2,"Xiaomi Mi Note 2":2,"Nokia Lumia 1020":2,"HTC One X10":2,"Gionee M7":2,"Samsung Galaxy J7 Max":2,"Gionee S6":2,"Samsung Galaxy J7":2,"Samsung Galaxy A5":2,"Motorola Moto Z Play":2,"Huawei Honor 8 Pro":2,"Oppo R7s":2,"Xiaomi Redmi Note 4X":1,"Nokia 3310":1,"Xiaomi Mi 6":1,"Apple iPhone 6s Plus":1,"Plum Ram 3G":1,"Motorola Moto G 4G Dual SIM":1,"HTC U Play":1,"Samsung Galaxy J7 Prime":1,"Motorola Moto G Turbo Edition":1,"Nokia Lumia 735":1,"Samsung Galaxy J1 Nxt":1,"XOLO Black":1,"Motorola Moto G5":1,"Meizu M1 Note":1,"BlackBerry Leap":1,"Sony Xperia M5":1,"Samsung Z3 Corporate Edition":1,"Motorola Moto M":1,"OnePlus 3T":1,"Samsung Galaxy A8":1,"Motorola Moto Maxx":1,"Apple iPhone 7":1,"Samsung Galaxy A7":1,"Motorola Moto Z":1,"LG K4":1,"Sony Xperia C5 Ultra":1,"Plum Ram 4":1,"Maxwest Nitro Phablet 71":1,"Xiaomi Mi Max":1,"Oppo R7 lite":1,"Meizu M2 Note":1,"Samsung Galaxy S7":1,"Huawei Honor 6C Pro":1,"Plum Ram Plus":1},"percent":{"alcatel Flash":2.2679692952,"OnePlus One":2.1632937893,"Motorola Moto X Play":1.2212142359,"Motorola Moto X Style":0.6978367062,"OnePlus 3":0.6629448709,"Xiaomi Redmi Note 4":0.5931612003,"Motorola Moto X":0.5931612003,"LG Nexus 5X":0.558269365,"Apple iPhone 5s":0.453593859,"Motorola Nexus 6":0.4187020237,"Xiaomi Redmi Note 5":0.4187020237,"Apple iPhone 6":0.3489183531,"OnePlus X":0.2791346825,"Asus Zenfone 3 Laser ZC551KL":0.2442428472,"Oppo A53":0.2093510119,"Oppo A57":0.2093510119,"Motorola Moto G":0.1744591766,"Google Pixel":0.1395673412,"Lenovo Vibe P1 Turbo":0.1395673412,"Xiaomi Mi 5":0.1395673412,"Apple iPhone 6 Plus":0.1395673412,"Xiaomi Mi Note 3":0.1395673412,"Apple iPhone 6s":0.1395673412,"BLU Advance 4.0 L3":0.1046755059,"Motorola Moto G4 Plus":0.1046755059,"verykool s4009 Crystal":0.1046755059,"Meizu MX5":0.1046755059,"YU Yutopia":0.0697836706,"Samsung Galaxy J5":0.0697836706,"Xiaomi Mi Note 2":0.0697836706,"Nokia Lumia 1020":0.0697836706,"HTC One X10":0.0697836706,"Gionee M7":0.0697836706,"Samsung Galaxy J7 Max":0.0697836706,"Gionee S6":0.0697836706,"Samsung Galaxy J7":0.0697836706,"Samsung Galaxy A5":0.0697836706,"Motorola Moto Z Play":0.0697836706,"Huawei Honor 8 Pro":0.0697836706,"Oppo R7s":0.0697836706,"Xiaomi Redmi Note 4X":0.0348918353,"Nokia 3310":0.0348918353,"Xiaomi Mi 6":0.0348918353,"Apple iPhone 6s Plus":0.0348918353,"Plum Ram 3G":0.0348918353,"Motorola Moto G 4G Dual SIM":0.0348918353,"HTC U Play":0.0348918353,"Samsung Galaxy J7 Prime":0.0348918353,"Motorola Moto G Turbo Edition":0.0348918353,"Nokia Lumia 735":0.0348918353,"Samsung Galaxy J1 Nxt":0.0348918353,"XOLO Black":0.0348918353,"Motorola Moto G5":0.0348918353,"Meizu M1 Note":0.0348918353,"BlackBerry Leap":0.0348918353,"Sony Xperia M5":0.0348918353,"Samsung Z3 Corporate Edition":0.0348918353,"Motorola Moto M":0.0348918353,"OnePlus 3T":0.0348918353,"Samsung Galaxy A8":0.0348918353,"Motorola Moto Maxx":0.0348918353,"Apple iPhone 7":0.0348918353,"Samsung Galaxy A7":0.0348918353,"Motorola Moto Z":0.0348918353,"LG K4":0.0348918353,"Sony Xperia C5 Ultra":0.0348918353,"Plum Ram 4":0.0348918353,"Maxwest Nitro Phablet 71":0.0348918353,"Xiaomi Mi Max":0.0348918353,"Oppo R7 lite":0.0348918353,"Meizu M2 Note":0.0348918353,"Samsung Galaxy S7":0.0348918353,"Huawei Honor 6C Pro":0.0348918353,"Plum Ram Plus":0.0348918353}}