{"categories": [{"num_posts": 2109, "sentiments": [0.0, 0.0, 0.275], "competitor_brands": {"LG": 21, "Nokia": 5, "Google": 19, "Honor": 9, "Samsung": 127, "Huawei": 25, "Xiaomi": 45, "Moto": 53, "Nexus": 8, "Sony": 41, "ZTE": 5, "OnePlus": 17, "BLU": 10, "HTC": 8, "BlackBerry": 3, "Nextbit": 1}, "competitor_models": {"Asus Zenfone 5Z": 447, "Google Pixel": 6, "Samsung Galaxy S7": 12, "Moto G": 4, "LG V10": 2, "Xiaomi Mi A1": 1, "Samsung Galaxy Note 4": 7, "Moto Z": 17, "LG G5": 7, "ZTE Axon 7": 2, "Samsung Galaxy S7 Edge": 11, "Sony Xperia Z3 Compact": 13, "Sony Xperia XA": 6, "BLU VIVO 8L": 10, "OnePlus 3": 10, "HTC Desire 825": 2, "OnePlus 3T": 1, "Google Pixel 2 XL": 1, "Nokia 7 Plus": 2, "Xiaomi Mi 5": 3, "Samsung Galaxy S6": 16, "Moto G4 Plus": 17, "Moto X Style": 2, "Huawei Nexus 6P": 1, "LG G4": 1, "Moto X": 6, "Huawei Mate 8": 1, "HTC One": 1}}]}