{"categories": [{"num_posts": 305, "sentiments": [0.0, 0.0642857142857143, 0.3125], "competitor_brands": {"Samsung": 15, "LG": 8, "OnePlus": 5, "Nokia": 3, "Moto": 1, "Google": 9, "ZTE": 1, "Xiaomi": 4, "Huawei": 1, "Sony": 3, "HTC": 1}, "competitor_models": {"OnePlus 3T": 2, "Nokia 7 Plus": 1, "LG G6": 2, "Google Pixel": 1, "Asus Zenfone 5Z": 20, "Samsung Galaxy S7 Edge": 1, "Samsung Galaxy Note 4": 1, "Sony Xperia Z5": 2, "LG V20": 3, "Samsung Galaxy S8": 1, "LG G5": 2, "Samsung Galaxy S7": 1, "OnePlus 3": 1}}]}