{"categories": [{"title": "Overall love", "rating": 4.5, "num_posts": 0, "sentiments": null, "competitor_brands": {}, "competitor_models": {}}, {"title": "Community development strength", "rating": 3.0, "num_posts": 0, "sentiments": null, "competitor_brands": {}, "competitor_models": {}}, {"title": "Overall speed", "rating": 5.0, "num_posts": 0, "sentiments": null, "competitor_brands": {}, "competitor_models": {}}, {"title": "App launch speed", "rating": 5.0, "num_posts": 0, "sentiments": null, "competitor_brands": {}, "competitor_models": {}}, {"title": "Multitasking/RAM", "rating": 4.5, "num_posts": 2, "sentiments": [0.11284722222222222, 0.19930555555555557, 0.2857638888888889], "competitor_brands": {"Google": 1}, "competitor_models": {"Google Pixel": 1}}, {"title": "Scrolling smoothness", "rating": 4.5, "num_posts": 0, "sentiments": null, "competitor_brands": {}, "competitor_models": {}}, {"title": "Heat", "rating": 4.0, "num_posts": 0, "sentiments": null, "competitor_brands": {}, "competitor_models": {}}, {"title": "Low light", "rating": 4.0, "num_posts": 0, "sentiments": null, "competitor_brands": {}, "competitor_models": {}}, {"title": "Photo quality", "rating": 5.0, "num_posts": 3, "sentiments": [0.0, 0.0, 0.049999999999999996], "competitor_brands": {}, "competitor_models": {}}, {"title": "Video quality", "rating": 5.0, "num_posts": 0, "sentiments": null, "competitor_brands": {}, "competitor_models": {}}, {"title": "Selfie quality", "rating": 5.0, "num_posts": 2, "sentiments": [0.2331845238095238, 0.24712301587301586, 0.26106150793650795], "competitor_brands": {}, "competitor_models": {"Sony Xperia XA": 1}}, {"title": "Time to take picture (camera launch speed)", "rating": 4.5, "num_posts": 0, "sentiments": null, "competitor_brands": {}, "competitor_models": {}}, {"title": "Software (ease of use, features, etc)", "rating": 5.0, "num_posts": 0, "sentiments": null, "competitor_brands": {}, "competitor_models": {}}, {"title": "Charging speed", "rating": 4.0, "num_posts": 2, "sentiments": [0.017499999999999995, 0.06833333333333333, 0.11916666666666667], "competitor_brands": {}, "competitor_models": {}}, {"title": "Screen on time", "rating": 4.0, "num_posts": 0, "sentiments": null, "competitor_brands": {}, "competitor_models": {}}, {"title": "Standby drain", "rating": 3.0, "num_posts": 0, "sentiments": null, "competitor_brands": {}, "competitor_models": {}}, {"title": "Heavy use endurance", "rating": 3.0, "num_posts": 1, "sentiments": [-0.5499999999999999, -0.5499999999999999, -0.5499999999999999], "competitor_brands": {}, "competitor_models": {}}, {"title": "Light use endurance", "rating": 4.0, "num_posts": 0, "sentiments": null, "competitor_brands": {}, "competitor_models": {}}, {"title": "\"Look\" of the device (aesthetics)", "rating": 5.0, "num_posts": 0, "sentiments": null, "competitor_brands": {}, "competitor_models": {}}, {"title": "Quality feel (use of materials)", "rating": 5.0, "num_posts": 2, "sentiments": [0.25, 0.3, 0.35000000000000003], "competitor_brands": {}, "competitor_models": {}}, {"title": "Ergonomics (in-hand feel)", "rating": 5.0, "num_posts": 0, "sentiments": null, "competitor_brands": {}, "competitor_models": {}}, {"title": "OEM skin/software", "rating": 4.5, "num_posts": 1, "sentiments": [0.0, 0.0, 0.0], "competitor_brands": {}, "competitor_models": {}}, {"title": "Outdoor visibility (max brightness)", "rating": 4.5, "num_posts": 1, "sentiments": [0.16, 0.16, 0.16], "competitor_brands": {}, "competitor_models": {}}, {"title": "Contrast (true blacks)", "rating": 5.0, "num_posts": 0, "sentiments": null, "competitor_brands": {}, "competitor_models": {}}, {"title": "Color saturation & accuracy", "rating": 5.0, "num_posts": 0, "sentiments": null, "competitor_brands": {}, "competitor_models": {}}, {"title": "Clarity/resolution", "rating": 5.0, "num_posts": 1, "sentiments": [-0.008333333333333326, -0.008333333333333326, -0.008333333333333326], "competitor_brands": {}, "competitor_models": {}}, {"title": "Minimum brightness", "rating": 4.0, "num_posts": 0, "sentiments": null, "competitor_brands": {}, "competitor_models": {}}, {"title": "Call quality", "rating": 5.0, "num_posts": 0, "sentiments": null, "competitor_brands": {}, "competitor_models": {}}, {"title": "WiFi strength, range, and throughput", "rating": 3.0, "num_posts": 5, "sentiments": [-0.05000000000000002, 0.0, 0.04166666666666666], "competitor_brands": {}, "competitor_models": {"Sony Xperia Z5": 1}}, {"title": "Cellular strength and throughput", "rating": 4.5, "num_posts": 0, "sentiments": null, "competitor_brands": {}, "competitor_models": {}}, {"title": "Speakerphone (loudness, clarity)", "rating": 4.5, "num_posts": 1, "sentiments": [0.26416666666666666, 0.26416666666666666, 0.26416666666666666], "competitor_brands": {}, "competitor_models": {"Sony Xperia Z3 Compact": 1}}]}