{"categories": [{"num_posts": 423, "sentiments": [0.0, 0.0, 0.25], "competitor_brands": {"LG": 16, "Honor": 9, "Huawei": 16, "OnePlus": 15, "Google": 2, "Xiaomi": 6, "Nokia": 1, "HTC": 2, "Asus": 1, "Sony": 2, "Moto": 1}, "competitor_models": {"Samsung Galaxy A8+": 62, "Honor 7X": 4, "OnePlus 5T": 13, "Samsung Galaxy S7 Edge": 8, "Samsung Galaxy S9": 7, "Google Pixel": 2, "Samsung Galaxy S8+": 4, "Samsung Galaxy S7": 5, "OnePlus 5": 1, "Huawei Mate 10": 9, "Samsung Galaxy Note 4": 4, "Samsung Galaxy S8": 2, "Samsung Galaxy S9+": 1, "Honor 9 Lite": 1, "Asus Zenfone 5Z": 1, "LG V10": 3, "LG G6": 4, "Samsung Galaxy S6": 2}}]}