{"categories": [{"num_posts": 2813, "sentiments": [0.0, 0.0, 0.28250000000000003], "competitor_brands": {"Moto": 16, "Sony": 45, "Google": 87, "Xiaomi": 23, "LG": 10, "Huawei": 19, "Nexus": 5, "Nokia": 9, "OnePlus": 32, "BLU": 4, "Asus": 12, "Honor": 4, "HTC": 10, "BlackBerry": 1}, "competitor_models": {"Samsung Galaxy Note 4": 18, "Samsung Galaxy S8+": 3, "Samsung Galaxy S7 Edge": 51, "Samsung Galaxy S6": 38, "Samsung Galaxy S7": 34, "OnePlus 3T": 18, "Sony Xperia Z3 Compact": 2, "Google Pixel": 12, "LG G6": 2, "Huawei P10": 3, "Xiaomi Mi 5": 4, "BLU VIVO 8L": 4, "Samsung Galaxy S9": 1, "Huawei Mate 8": 7, "Asus Zenfone 5Z": 9, "Nokia 7 Plus": 2, "Sony Xperia XA": 12, "OnePlus 2": 1, "HTC 10": 2, "HTC Desire 825": 1, "Sony Xperia Z5": 4, "LG G4": 1, "Moto Z": 10, "Moto X": 2, "LG G5": 5, "OnePlus 3": 11, "Moto X Style": 1, "HTC One": 1, "Sony Xperia X Performance": 1}}]}