{"bad boyz nougat":{"occurences":2,"sentimentsSummary":[-0.5687,-0.4375,-0.3062]},"call quality":{"occurences":2,"sentimentsSummary":[-0.525,-0.35,-0.175]},"signal strength":{"occurences":6,"sentimentsSummary":[-0.3667,-0.1333,0.0375]},"car":{"occurences":4,"sentimentsSummary":[-0.15,0.0,0.0833]},"6 hrs":{"occurences":3,"sentimentsSummary":[-0.15,-0.15,-0.075]},"mobile data":{"occurences":4,"sentimentsSummary":[-0.1344,-0.0458,-0.0188]},"same time":{"occurences":3,"sentimentsSummary":[-0.0885,-0.0312,-0.0156]},"previous phones":{"occurences":2,"sentimentsSummary":[-0.0833,-0.025,0.0333]},"other phones":{"occurences":5,"sentimentsSummary":[-0.0625,-0.0208,-0.0125]},"same signal strength":{"occurences":3,"sentimentsSummary":[-0.05,0.0,0.025]}}