{"categories": [{"title": "Overall love", "rating": 4.0, "num_posts": 3, "sentiments": [0.10892857142857142, 0.21785714285714283, 0.27787114845938377], "competitor_brands": {"Google": 1, "Samsung": 1}, "competitor_models": {"Samsung Galaxy J7": 1, "Google Pixel 2": 1}}, {"title": "Community development strength", "rating": 1.0, "num_posts": 0, "sentiments": null, "competitor_brands": {}, "competitor_models": {}}, {"title": "Overall speed", "rating": 4.0, "num_posts": 0, "sentiments": null, "competitor_brands": {}, "competitor_models": {}}, {"title": "App launch speed", "rating": 4.0, "num_posts": 0, "sentiments": null, "competitor_brands": {}, "competitor_models": {}}, {"title": "Multitasking/RAM", "rating": 4.0, "num_posts": 0, "sentiments": null, "competitor_brands": {}, "competitor_models": {}}, {"title": "Scrolling smoothness", "rating": 4.5, "num_posts": 0, "sentiments": null, "competitor_brands": {}, "competitor_models": {}}, {"title": "Heat", "rating": 4.5, "num_posts": 0, "sentiments": null, "competitor_brands": {}, "competitor_models": {}}, {"title": "Low light", "rating": 4.5, "num_posts": 3, "sentiments": [0.36250000000000004, 0.425, 0.42678571428571427], "competitor_brands": {"OnePlus": 1, "Google": 1}, "competitor_models": {}}, {"title": "Photo quality", "rating": 4.0, "num_posts": 0, "sentiments": null, "competitor_brands": {}, "competitor_models": {}}, {"title": "Video quality", "rating": 0.0, "num_posts": 0, "sentiments": null, "competitor_brands": {}, "competitor_models": {}}, {"title": "Selfie quality", "rating": 0.0, "num_posts": 0, "sentiments": null, "competitor_brands": {}, "competitor_models": {}}, {"title": "Time to take picture (camera launch speed)", "rating": 1.0, "num_posts": 2, "sentiments": [-0.07263888888888889, -0.00027777777777777957, 0.07208333333333333], "competitor_brands": {}, "competitor_models": {}}, {"title": "Software (ease of use, features, etc)", "rating": 0.0, "num_posts": 0, "sentiments": null, "competitor_brands": {}, "competitor_models": {}}, {"title": "Charging speed", "rating": 4.0, "num_posts": 0, "sentiments": null, "competitor_brands": {}, "competitor_models": {}}, {"title": "Screen on time", "rating": 5.0, "num_posts": 1, "sentiments": [0.17142857142857146, 0.17142857142857146, 0.17142857142857146], "competitor_brands": {}, "competitor_models": {}}, {"title": "Standby drain", "rating": 5.0, "num_posts": 0, "sentiments": null, "competitor_brands": {}, "competitor_models": {}}, {"title": "Heavy use endurance", "rating": 3.0, "num_posts": 1, "sentiments": [0.0, 0.0, 0.0], "competitor_brands": {}, "competitor_models": {}}, {"title": "Light use endurance", "rating": 5.0, "num_posts": 0, "sentiments": null, "competitor_brands": {}, "competitor_models": {}}, {"title": "\"Look\" of the device (aesthetics)", "rating": 5.0, "num_posts": 0, "sentiments": null, "competitor_brands": {}, "competitor_models": {}}, {"title": "Quality feel (use of materials)", "rating": 4.0, "num_posts": 0, "sentiments": null, "competitor_brands": {}, "competitor_models": {}}, {"title": "Ergonomics (in-hand feel)", "rating": 5.0, "num_posts": 0, "sentiments": null, "competitor_brands": {}, "competitor_models": {}}, {"title": "OEM skin/software", "rating": 3.5, "num_posts": 2, "sentiments": [0.0, 0.0, 0.0], "competitor_brands": {}, "competitor_models": {}}, {"title": "Outdoor visibility (max brightness)", "rating": 4.0, "num_posts": 0, "sentiments": null, "competitor_brands": {}, "competitor_models": {}}, {"title": "Contrast (true blacks)", "rating": 4.0, "num_posts": 0, "sentiments": null, "competitor_brands": {}, "competitor_models": {}}, {"title": "Color saturation & accuracy", "rating": 3.0, "num_posts": 1, "sentiments": [-0.2, -0.2, -0.2], "competitor_brands": {}, "competitor_models": {}}, {"title": "Clarity/resolution", "rating": 5.0, "num_posts": 0, "sentiments": null, "competitor_brands": {}, "competitor_models": {}}, {"title": "Minimum brightness", "rating": 4.0, "num_posts": 0, "sentiments": null, "competitor_brands": {}, "competitor_models": {}}, {"title": "Call quality", "rating": 3.0, "num_posts": 0, "sentiments": null, "competitor_brands": {}, "competitor_models": {}}, {"title": "WiFi strength, range, and throughput", "rating": 4.0, "num_posts": 0, "sentiments": null, "competitor_brands": {}, "competitor_models": {}}, {"title": "Cellular strength and throughput", "rating": 4.5, "num_posts": 1, "sentiments": [0.5, 0.5, 0.5], "competitor_brands": {}, "competitor_models": {"HTC 10": 1}}, {"title": "Speakerphone (loudness, clarity)", "rating": 4.0, "num_posts": 0, "sentiments": null, "competitor_brands": {}, "competitor_models": {}}]}